{"inkVersion":21,"root":[["\n","ev",{"VAR?":"fettsackRep"},0,">","/ev",[{"->":".^.b","c":true},{"b":["^ ",{"->":"goodRep"},{"->":"0.8"},null]}],[{"->":".^.b"},{"b":["^ ",{"->":"badRep"},{"->":"0.8"},null]}],"nop","\n",["done",{"#f":5,"#n":"g-0"}],null],"done",{"goodRep":[["^Hey Bongo, weißt du wer heute Morgen die geniale Idee hatte Chickenwings zu bestellen? Haha!","\n","^ICH! argh","\n","ev","str","^Glückwunsch.","/str","/ev",{"*":".^.c-0","flg":20},"ev","str","^Klar, du bist der wahre Trendsetter. Was kommt als nächstes? Pommes mit Ketchup?","/str","/ev",{"*":".^.c-1","flg":20},{"c-0":["^ ","#","^rage:0 ","/#","#","^rep:-1","/#","\n",{"->":"end1"},{"#f":5}],"c-1":["#","^rage:-1 ","/#","#","^rep:2","/#","\n",{"->":"end2"},{"#f":5}]}],{"#f":1}],"end1":["^Hehe! Guter Gaumenschmaus du kleine Laus! Haha!","\n","done",{"#f":1}],"badRep":[["^Hey mein Freund, na weißt du wer heute Morgen die geniale Idee hatte Chickenwings zu bestellen? Haha!","\n","^ICH! Haha!","\n","ev","str","^Glückwunsch! Dann pass auf, dass du nicht wegfliegst!","/str","/ev",{"*":".^.c-0","flg":20},"ev","str","^Klar, du bist der wahre Trendsetter. Was kommt als nächstes? Pommes mit Ketchup?","/str","/ev",{"*":".^.c-1","flg":20},{"c-0":["\n",{"->":"end3"},{"#f":5}],"c-1":["#","^rage:0 ","/#","#","^rep:-1","/#","\n",{"->":"end2"},{"#f":5}]}],{"#f":1}],"end2":["^Spielverderber! Du weißt ja gar nicht, was gutes Gourmetessen ist!","\n","done",{"#f":1}],"end3":["^Haha! Du machst ja ein auf witzig! Gefällt mir! ","#","^rage:-1 ","/#","#","^rep:2","/#","\n","done",{"#f":1}],"global decl":["ev","str","^","/str",{"VAR=":"pokemonName"},-1,{"VAR=":"fettsackRep"},"/ev","end",null],"#f":1}],"listDefs":{}}